MANIFEST.in
README.rst
requirements.txt
setup.py
lisa/__init__.py
lisa/plugins/__init__.py
lisa/plugins/Shopping/README.rst
lisa/plugins/Shopping/__init__.py
lisa/plugins/Shopping/shopping.json
lisa/plugins/Shopping/lang/en/LC_MESSAGES/shopping.po
lisa/plugins/Shopping/lang/fr/LC_MESSAGES/shopping.mo
lisa/plugins/Shopping/lang/fr/LC_MESSAGES/shopping.po
lisa/plugins/Shopping/modules/__init__.py
lisa/plugins/Shopping/modules/shopping.py
lisa/plugins/Shopping/web/__init__.py
lisa/plugins/Shopping/web/api.py
lisa/plugins/Shopping/web/models.py
lisa/plugins/Shopping/web/tests.py
lisa/plugins/Shopping/web/urls.py
lisa/plugins/Shopping/web/views.py
lisa/plugins/UnitTest/__init__.py
lisa/plugins/UnitTest/unittest.json
lisa/plugins/UnitTest/lang/fr/LC_MESSAGES/unittest.mo
lisa/plugins/UnitTest/lang/fr/LC_MESSAGES/unittest.po
lisa/plugins/UnitTest/modules/__init__.py
lisa/plugins/UnitTest/modules/unittest.py
lisa/plugins/UnitTest/test/__init__.py
lisa/plugins/UnitTest/test/chat_test.py
lisa/plugins/UnitTest/web/__init__.py
lisa/plugins/UnitTest/web/api.py
lisa/plugins/UnitTest/web/models.py
lisa/plugins/UnitTest/web/tests.py
lisa/plugins/UnitTest/web/urls.py
lisa/plugins/UnitTest/web/views.py
lisa/server/ConfigManager.py
lisa/server/__init__.py
lisa/server/lisa-cli
lisa/server/service.py
lisa/server/tap.py
lisa/server/configuration/lisa.json.sample
lisa/server/configuration/ssl/server.crt
lisa/server/configuration/ssl/server.key
lisa/server/configuration/ssl/server.pem
lisa/server/configuration/ssl/websocket.key
lisa/server/configuration/ssl/public/client-1.crt
lisa/server/configuration/ssl/public/websocket.crt
lisa/server/core/__init__.py
lisa/server/core/intents.py
lisa/server/lang/es/LC_MESSAGES/intents.po
lisa/server/lang/es/LC_MESSAGES/lisa.po
lisa/server/lang/fr/LC_MESSAGES/intents.mo
lisa/server/lang/fr/LC_MESSAGES/intents.po
lisa/server/lang/fr/LC_MESSAGES/lisa.mo
lisa/server/lang/fr/LC_MESSAGES/lisa.po
lisa/server/lang/sv/LC_MESSAGES/intents.po
lisa_server.egg-info/PKG-INFO
lisa_server.egg-info/SOURCES.txt
lisa_server.egg-info/dependency_links.txt
lisa_server.egg-info/namespace_packages.txt
lisa_server.egg-info/requires.txt
lisa_server.egg-info/top_level.txt
